bigtools/__init__.py
bigtools/auth_tools.py
bigtools/db_tools.py
bigtools/default_data.py
bigtools/download_tools.py
bigtools/email_tools.py
bigtools/exception_tools.py
bigtools/file_tools.py
bigtools/hash_tools.py
bigtools/jieba_tools.py
bigtools/json_tools.py
bigtools/log_tools.py
bigtools/more_tools.py
bigtools/path_tools.py
bigtools/print_tools.py
bigtools/similarity_tools.py
bigtools/similarity_tools_async.py
bigtools/stop_words.py
bigtools/yaml_tools.py
bigtools-1.4.4.dist-info/licenses/LICENSE
bigtools-1.4.4.dist-info/METADATA
bigtools-1.4.4.dist-info/WHEEL
bigtools-1.4.4.dist-info/top_level.txt
bigtools-1.4.4.dist-info/RECORD
