Metadata-Version: 2.4
Name: bigtools
Version: 1.4.4
Summary: Tools for python
Author-email: hongbo liu <bananabo@foxmail.com>
License: Apache-2.0
Project-URL: Homepage, https://gitee.com/maxbanana
Classifier: Programming Language :: Python :: 3
Classifier: License :: OSI Approved :: Apache Software License
Classifier: Operating System :: OS Independent
Requires-Python: >=3.9
License-File: LICENSE
Requires-Dist: requests>=2.31.0
Requires-Dist: tqdm>=4.66.1
Requires-Dist: lxml>=4.9.3
Requires-Dist: pymongo>=4.5.0
Requires-Dist: pytz>=2023.3
Requires-Dist: jsonschema>=4.19.1
Requires-Dist: PyYAML>=6.0.1
Requires-Dist: jieba==0.42.1
Requires-Dist: minio>=7.2.5
Requires-Dist: motor>3.7.0
Requires-Dist: redis>=6.4.0
Requires-Dist: aiohttp>=3.12.15
Requires-Dist: aiofiles>=24.1.0
Requires-Dist: orjson>=3.11.3
Requires-Dist: numpy>=1.26.4
Requires-Dist: scikit-learn>=1.7.2
Requires-Dist: bm25s>=0.2.14
Requires-Dist: elasticsearch>=8.14.0
Dynamic: license-file
